odoo/addons/account_cutoff_accrual_purchase/README.rst
odoo/addons/account_cutoff_accrual_purchase/__init__.py
odoo/addons/account_cutoff_accrual_purchase/__manifest__.py
odoo/addons/account_cutoff_accrual_purchase/hooks.py
odoo/addons/account_cutoff_accrual_purchase/data/ir_cron.xml
odoo/addons/account_cutoff_accrual_purchase/i18n/account_cutoff_accrual_purchase.pot
odoo/addons/account_cutoff_accrual_purchase/i18n/fr.po
odoo/addons/account_cutoff_accrual_purchase/i18n/it.po
odoo/addons/account_cutoff_accrual_purchase/models/__init__.py
odoo/addons/account_cutoff_accrual_purchase/models/account_cutoff.py
odoo/addons/account_cutoff_accrual_purchase/models/account_cutoff_line.py
odoo/addons/account_cutoff_accrual_purchase/models/account_move.py
odoo/addons/account_cutoff_accrual_purchase/models/purchase_order.py
odoo/addons/account_cutoff_accrual_purchase/models/purchase_order_line.py
odoo/addons/account_cutoff_accrual_purchase/readme/CONFIGURE.rst
odoo/addons/account_cutoff_accrual_purchase/readme/CONTRIBUTORS.rst
odoo/addons/account_cutoff_accrual_purchase/readme/DESCRIPTION.rst
odoo/addons/account_cutoff_accrual_purchase/readme/USAGE.rst
odoo/addons/account_cutoff_accrual_purchase/static/description/icon.png
odoo/addons/account_cutoff_accrual_purchase/static/description/index.html
odoo/addons/account_cutoff_accrual_purchase/views/account_cutoff.xml
odoo/addons/account_cutoff_accrual_purchase/views/account_cutoff_line.xml
odoo_addon_account_cutoff_accrual_purchase-16.0.1.0.0.4.dist-info/METADATA
odoo_addon_account_cutoff_accrual_purchase-16.0.1.0.0.4.dist-info/WHEEL
odoo_addon_account_cutoff_accrual_purchase-16.0.1.0.0.4.dist-info/top_level.txt
odoo_addon_account_cutoff_accrual_purchase-16.0.1.0.0.4.dist-info/RECORD
