Metadata-Version: 2.1
Name: odoo-addon-account_cutoff_accrual_purchase
Version: 16.0.1.0.0.4
Summary: Accrued Expense on Purchase Order
Home-page: https://github.com/OCA/account-closing
Author: BCIM, Odoo Community Association (OCA)
Author-email: support@odoo-community.org
License: AGPL-3
Classifier: Programming Language :: Python
Classifier: Framework :: Odoo
Classifier: Framework :: Odoo :: 16.0
Classifier: License :: OSI Approved :: GNU Affero General Public License v3
Requires-Python: >=3.10
Requires-Dist: odoo-addon-account-cutoff-accrual-order-base<16.1dev,>=16.0dev
Requires-Dist: odoo-addon-purchase-force-invoiced<16.1dev,>=16.0dev
Requires-Dist: odoo<16.1dev,>=16.0a
